gradio_i18n/__init__.py
gradio_i18n/i18n.py
gradio_i18n-0.3.4.dist-info/METADATA
gradio_i18n-0.3.4.dist-info/WHEEL
gradio_i18n-0.3.4.dist-info/licenses/LICENSE
gradio_i18n-0.3.4.dist-info/RECORD
