Metadata-Version: 2.4
Name: gradio-i18n
Version: 0.3.4
Summary: Reactive Multi-language Gradio App with minimal effort
Project-URL: Homepage, https://github.com/hoveychen/gradio-i18n
Project-URL: Issues, https://github.com/hoveychen/gradio-i18n/issues
Author-email: Harry Chen <hoveychen@gmail.com>
License-File: LICENSE
Classifier: Intended Audience :: Developers
Classifier: License :: OSI Approved :: Apache Software License
Classifier: Operating System :: OS Independent
Classifier: Programming Language :: Python :: 3
Classifier: Topic :: Software Development :: Libraries :: Python Modules
Requires-Python: >=3.8
Requires-Dist: gradio>=4.32
Requires-Dist: langcodes<3.5
Requires-Dist: pyyaml
